CHANGES.rst
MANIFEST.in
README.rst
setup.py
djorm_hstore_editor.egg-info/PKG-INFO
djorm_hstore_editor.egg-info/SOURCES.txt
djorm_hstore_editor.egg-info/dependency_links.txt
djorm_hstore_editor.egg-info/not-zip-safe
djorm_hstore_editor.egg-info/requires.txt
djorm_hstore_editor.egg-info/top_level.txt
hstore_editor/__init__.py
hstore_editor/fields.py
hstore_editor/models.py
hstore_editor/version.py
hstore_editor/widgets.py
hstore_editor/locale/ru/LC_MESSAGES/django.mo
hstore_editor/static/hstore_editor/hstore_editor.css