Metadata-Version: 1.1
Name: djorm-hstore-editor
Version: 0.1.0
Summary: djorm-ext-hstore extension
Home-page: https://github.com/Yuego/djorm-hstore-editor
Author: Artem Vlasov
Author-email: root@proscript.ru
License: MIT
Platform: OS Independent
Classifier: Development Status :: 4 - Beta
Classifier: Framework :: Django
Classifier: Intended Audience :: Developers
Classifier: License :: OSI Approved :: BSD License
Classifier: Operating System :: OS Independent
Classifier: Topic :: Internet :: WWW/HTTP
Classifier: Programming Language :: Python
Classifier: Programming Language :: Python :: 2.7
Classifier: Programming Language :: Python :: 3
Classifier: Programming Language :: Python :: 3.3
